{
	"1": {
		"name": "冥火",
		"nature": 1,
		"desc": "我方墓地地狱卡牌数量大于1张时,发动烈火焚身3(每局最多发动4次)",
		"nums": 2,
		"star": 4,
		"skill": {
			"1": {
				"level": 2,
				"enableLevel": 0
			}
		}
	},
	"2": {
		"name": "冥火",
		"nature": 1,
		"desc": "我方墓地地狱卡牌数量大于1张时,发动烈火焚身3(每局最多发动4次)",
		"nums": 2,
		"star": 4,
		"skill": {
			"1": {
				"level": 2,
				"enableLevel": 0
			}
		}
	},
	"3": {
		"name": "冥火",
		"nature": 1,
		"desc": "我方墓地地狱卡牌数量大于1张时,发动烈火焚身3(每局最多发动4次)",
		"nums": 2,
		"star": 4,
		"skill": {
			"1": {
				"level": 2,
				"enableLevel": 0
			}
		}
	},
	"4": {
		"name": "冥火",
		"nature": 1,
		"desc": "我方墓地地狱卡牌数量大于1张时,发动烈火焚身3(每局最多发动4次)",
		"nums": 2,
		"star": 4,
		"skill": {
			"1": {
				"level": 2,
				"enableLevel": 0
			}
		}
	},
	"5": {
		"name": "冥火",
		"nature": 1,
		"desc": "我方墓地地狱卡牌数量大于1张时,发动烈火焚身3(每局最多发动4次)",
		"nums": 2,
		"star": 4,
		"skill": {
			"1": {
				"level": 2,
				"enableLevel": 0
			}
		}
	},
	"6": {
		"name": "冥火",
		"nature": 1,
		"desc": "我方墓地地狱卡牌数量大于1张时,发动烈火焚身3(每局最多发动4次)",
		"nums": 2,
		"star": 4,
		"skill": {
			"1": {
				"level": 2,
				"enableLevel": 0
			}
		}
	},
	"7": {
		"name": "冥火",
		"nature": 1,
		"desc": "我方墓地地狱卡牌数量大于1张时,发动烈火焚身3(每局最多发动4次)",
		"nums": 2,
		"star": 4,
		"skill": {
			"1": {
				"level": 2,
				"enableLevel": 0
			}
		}
	},
	"8": {
		"name": "冥火",
		"nature": 1,
		"desc": "我方墓地地狱卡牌数量大于1张时,发动烈火焚身3(每局最多发动4次)",
		"nums": 2,
		"star": 4,
		"skill": {
			"1": {
				"level": 2,
				"enableLevel": 0
			}
		}
	},
	"9": {
		"name": "冥火",
		"nature": 1,
		"desc": "我方墓地地狱卡牌数量大于1张时,发动烈火焚身3(每局最多发动4次)",
		"nums": 2,
		"star": 4,
		"skill": {
			"1": {
				"level": 2,
				"enableLevel": 0
			}
		}
	},
	"10": {
		"name": "冥火",
		"nature": 1,
		"desc": "我方墓地地狱卡牌数量大于1张时,发动烈火焚身3(每局最多发动4次)",
		"nums": 2,
		"star": 4,
		"skill": {
			"1": {
				"level": 2,
				"enableLevel": 0
			}
		}
	},
	"11": {
		"name": "冥火",
		"nature": 1,
		"desc": "我方墓地地狱卡牌数量大于1张时,发动烈火焚身3(每局最多发动4次)",
		"nums": 2,
		"star": 4,
		"skill": {
			"1": {
				"level": 2,
				"enableLevel": 0
			}
		}
	},
	"12": {
		"name": "冥火",
		"nature": 1,
		"desc": "我方墓地地狱卡牌数量大于1张时,发动烈火焚身3(每局最多发动4次)",
		"nums": 2,
		"star": 4,
		"skill": {
			"1": {
				"level": 2,
				"enableLevel": 0
			}
		}
	}
}